aimmocore_db/__init__.py
aimmocore_db/install_mongodb.py
aimmocore_db/src/__init__.py
aimmocore_db-0.1.22.dist-info/LICENSE
aimmocore_db-0.1.22.dist-info/METADATA
aimmocore_db-0.1.22.dist-info/WHEEL
aimmocore_db-0.1.22.dist-info/top_level.txt
aimmocore_db-0.1.22.dist-info/RECORD
